githubaudit/__init__.py
githubaudit/audit.py
githubaudit/cli.py
githubaudit/github.py
githubaudit/output.py
githubaudit/utils.py
githubaudit/templates/layout.html
githubaudit/templates/table.html
githubaudit-0.1.3.dist-info/LICENSE
githubaudit-0.1.3.dist-info/METADATA
githubaudit-0.1.3.dist-info/WHEEL
githubaudit-0.1.3.dist-info/entry_points.txt
githubaudit-0.1.3.dist-info/top_level.txt
githubaudit-0.1.3.dist-info/RECORD
