Metadata-Version: 2.1
Name: githubaudit
Version: 0.1.3
Summary: Uses a Github PAT to assess the security configuration of repositories and provides a report
Home-page: https://github.com/nopcorn/githubaudit
Author: nopcorn
Author-email: 
Classifier: Development Status :: 5 - Production/Stable
Classifier: Environment :: Console
Classifier: Intended Audience :: Developers
Classifier: Intended Audience :: System Administrators
Classifier: License :: OSI Approved :: GNU General Public License v3 (GPLv3)
Classifier: Operating System :: OS Independent
Classifier: Programming Language :: Python :: 3
Classifier: Programming Language :: Python :: 3.7
Classifier: Programming Language :: Python :: 3.8
Classifier: Programming Language :: Python :: 3.9
Classifier: Programming Language :: Python :: 3.10
Classifier: Programming Language :: Python :: 3.11
Classifier: Topic :: Security
Requires-Python: >=3.7
License-File: LICENSE
Requires-Dist: requests ==2.32.3
Requires-Dist: jinja2
